README.rst
setup.py
zlapp/__init__.py
zlapp/api.py
zlapp.egg-info/PKG-INFO
zlapp.egg-info/SOURCES.txt
zlapp.egg-info/dependency_links.txt
zlapp.egg-info/requires.txt
zlapp.egg-info/top_level.txt
zlapp/cdc/__init__.py
zlapp/cdc/api.py
zlapp/cdc/app_qy_query.py
zlapp/cdc/app_qy_zcry.py
zlapp/cdc/app_qy_zz.py
zlapp/cdc/app_ry_query.py
zlapp/cdc/bd_dt.py
zlapp/cdc/gg.py
zlapp/cdc/gg_html.py
zlapp/cdc/gg_html_algo.py
zlapp/cdc/gg_meta.py
zlapp/cdc/gg_zhongbiao.py
zlapp/cdc/qy_zhongbiao.py
zlapp/cdc/t_bd_xflv.py
zlapp/cdc/t_gg_ent_bridge.py
zlapp/cdc/tool.py
zlapp/cdc/xmjl_zhongbiao.py
zlapp/function/__init__.py
zlapp/function/api.py
zlapp/grant/__init__.py
zlapp/grant/app206.py
zlapp/greenplum/__init__.py
zlapp/greenplum/api.py
zlapp/greenplum/api_dag.py
zlapp/greenplum/app_gg_zhongbiao.py
zlapp/greenplum/app_qy_query.py
zlapp/greenplum/app_qy_zcry.py
zlapp/greenplum/app_qy_zz.py
zlapp/greenplum/app_ry_query.py
zlapp/greenplum/bd.py
zlapp/greenplum/bd_dt.py
zlapp/greenplum/core_pxf.py
zlapp/greenplum/entrank.py
zlapp/greenplum/gg.py
zlapp/greenplum/gg_html.py
zlapp/greenplum/gg_html_algo.py
zlapp/greenplum/gg_meta.py
zlapp/greenplum/gg_zhongbiao.py
zlapp/greenplum/html_key_xflv.py
zlapp/greenplum/qy_base.py
zlapp/greenplum/qy_zcry.py
zlapp/greenplum/qy_zhongbiao.py
zlapp/greenplum/qy_zz.py
zlapp/greenplum/t_bd_xflv.py
zlapp/greenplum/t_gg_ent_bridge.py
zlapp/greenplum/t_person.py
zlapp/greenplum/xmjl_zhongbiao.py
zlapp/zlshenpi/__init__.py
zlapp/zlshenpi/all.py
zlapp/zlshenpi/core.py
zlapp/zlshenpi/est.py
zlapp/zlshenpi/fujiansheng.py
zlapp/zlshenpi/zlshenpi_work.py
zlapp/zz/__init__.py
zlapp/zz/qiyezz.py
zlapp/zz/zcry.py